scripts/__init__.py
soa_report/__init__.py
soa_report/scenario_reporter_cmd.py
soa_report/segmentation_reporter_cmd.py
soa_report/commons/__init__.py
soa_report/commons/env_variables.py
soa_report/commons/matplotlib_utils.py
soa_report/commons/my_log.py
soa_report/commons/plots_utils.py
soa_report/commons/power_pwr.py
soa_report/commons/rst_report.py
soa_report/commons/spice_kernel_utils.py
soa_report/juice/__init__.py
soa_report/juice/scenario_reporter.py
soa_report/juice/segmentation_reporter.py
soa_report/juice/eps_data/__init__.py
soa_report/juice/eps_data/brf.py
soa_report/juice/eps_data/data_rate_avg.py
soa_report/juice/eps_data/df_brf.py
soa_report/juice/eps_data/df_data_latency.py
soa_report/juice/eps_data/df_data_rate_avg.py
soa_report/juice/eps_data/df_power_avg.py
soa_report/juice/eps_data/ds_latency.py
soa_report/juice/eps_data/ds_transfers.py
soa_report/juice/eps_data/epsoutput.py
soa_report/juice/eps_data/file_latency.py
soa_report/juice/eps_data/power_avg.py
soa_report/juice/report/__init__.py
soa_report/juice/report/soa_report_basics.py
soa_report/juice/report/soa_report_summary.py
soa_report/juice/segmentation/__init__.py
soa_report/juice/segmentation/power_metrics.py
soa_report/juice/soa/__init__.py
soa_report/juice/soa/power_metrics.py
soa_report/juice/soa/scenario_compare.py
soa_report/juice/soa/soa_report_basics.py
soa_report/juice/templates/custom-reference.docx
soa_report/juice/templates/default_rst2pdf.style
soa_report/templates/Segmentation_Reporter_Configuration_file.json
soa_report/templates/__init__.py
soa_report/templates/scenario_reporter.json
soa_report/utest/__init__.py
soa_report/utest/utest_epsdata_brf_handling.py
test/__init__.py
test/test_scenario_report_e2e.py
test/test_segmentation_report_e2e.py
test/test_segmentation_report_e2e_not_osve.py
test/test_segmentation_report_e2e_overwrite.py
soa_report-1.2.7.dist-info/METADATA
soa_report-1.2.7.dist-info/WHEEL
soa_report-1.2.7.dist-info/entry_points.txt
soa_report-1.2.7.dist-info/top_level.txt
soa_report-1.2.7.dist-info/RECORD
